mycityco2_data_process/__init__.py
mycityco2_data_process/__main__.py
mycityco2_data_process/cli/__init__.py
mycityco2_data_process/cli/cli.py
mycityco2_data_process/const.py
mycityco2_data_process/data/common/carbon_factor_mapping.xlsx
mycityco2_data_process/data/common/odoo.conf
mycityco2_data_process/data/fr/coa_categories.csv
mycityco2_data_process/data/fr/coa_condition.csv
mycityco2_data_process/data/fr/departement/26.csv
mycityco2_data_process/data/fr/departement/2A.csv
mycityco2_data_process/data/fr/fr_mapping_coa_exiobase.csv
mycityco2_data_process/data/fr/fr_mapping_immo_exiobase.csv
mycityco2_data_process/data/fr/postal.csv
mycityco2_data_process/data/fr/readme.md
mycityco2_data_process/data/fr/siren.csv
mycityco2_data_process/data/readme.md
mycityco2_data_process/importer/__init__.py
mycityco2_data_process/importer/base.py
mycityco2_data_process/importer/fr.py
mycityco2_data_process/logger.py
mycityco2_data_process/runner.py
mycityco2_data_process/utils.py
mycityco2_data_process/wrapper.py
mycityco2_data_process-0.2.1.dist-info/LICENSE
mycityco2_data_process-0.2.1.dist-info/METADATA
mycityco2_data_process-0.2.1.dist-info/WHEEL
mycityco2_data_process-0.2.1.dist-info/entry_points.txt
mycityco2_data_process-0.2.1.dist-info/RECORD
