Metadata-Version: 2.1
Name: mycityco2-data-process
Version: 0.2.1
Summary: 
Home-page: https://github.com/MyCityCO2/mycityco2-data-processing
Author: Adam Bonnet
Author-email: contact@mycityco2.org
Requires-Python: >=3.8,<4.0
Classifier: Programming Language :: Python :: 3
Classifier: Programming Language :: Python :: 3.8
Classifier: Programming Language :: Python :: 3.9
Classifier: Programming Language :: Python :: 3.10
Classifier: Programming Language :: Python :: 3.11
Requires-Dist: bs4 (>=0.0.1,<0.0.2)
Requires-Dist: discord-webhook (>=1.1.0,<2.0.0)
Requires-Dist: docker (>=6.1.3,<7.0.0)
Requires-Dist: gitpython (>=3.1.40,<4.0.0)
Requires-Dist: loguru (>=0.7.0,<0.8.0)
Requires-Dist: lxml (>=4.9.2,<5.0.0)
Requires-Dist: multiprocess (>=0.70.14,<0.71.0)
Requires-Dist: openpyxl (>=3.1.2,<4.0.0)
Requires-Dist: otools-rpc (==0.5.0)
Requires-Dist: pandas (>=2.0.2,<3.0.0)
Requires-Dist: psycopg2-binary (>=2.9.6,<3.0.0)
Requires-Dist: pydantic[dotenv] (>=1.10.8,<2.0.0)
Requires-Dist: typer[all] (>=0.9.0,<0.10.0)
Requires-Dist: xmltodict (>=0.13.0,<0.14.0)
Project-URL: Repository, https://github.com/MyCityCO2/mycityco2-data-processing
